[{"OBJECTID": 0,
  "COUNTY": "DUBLIN",
"ENGLISH": "Dublin City",
"CONTAE": "Baile Átha Cliath",
"POPULATION": 554554,
"PREVPOPULATION": 527612,
"MALES": "272,270",
"FEMALES": "282,284",
"HOUSESTOCK": "240,553",
"VACANT": "18,424",
"AREA": "115 km²",
"AGE": "37.9",
"ABOUT": "Dublin City Council (DCC) is the authority responsible for local government in the city of Dublin and has 9 local electoral areas. ",
"GAEILGE": " ",
"PROVINCE": "Leinster",
"ID": "265011",
"CENTROID_X": "712153",
"CENTROID_Y": "735780",
"GlobalID": "ec7df314-e9ad-4b31-b76c-e3ce8796a87c",
"GUID": "EC7DF314-E9AD-4B31-B76C-E3CE8796A87C",
"Shape__Area": 0.0173265844470448,
"Shape__Length": 1.25844625628791},
{"OBJECTID": 1,
"COUNTY": "DUBLIN",
"ENGLISH": "South Dublin",
"CONTAE": "Baile Átha Cliath",
"POPULATION": 278767,
"PREVPOPULATION": 265205,
"MALES": "136,277",
"FEMALES": "142,490",
"HOUSESTOCK": "98,387",
"VACANT": "3,495",
"AREA": "222.7 km²",
"AGE": "35.5",
"ABOUT": "South Dublin County Council (SDCC) is the authority responsible for local government in the county of South Dublin and has 6 local electoral areas. ",
"GAEILGE": " ",
"PROVINCE": "Leinster",
"ID": "265003",
"CENTROID_X": "704391",
"CENTROID_Y": "726785",
"GlobalID": "6c7d5f02-1d93-42bf-9b2e-91ce53906e32",
"GUID": "6C7D5F02-1D93-42BF-9B2E-91CE53906E32",
"Shape__Area": 0.0300972950901327,
"Shape__Length": 1.1222813249711},
{"OBJECTID": 2,
"COUNTY": "DUBLIN",
"ENGLISH": "Fingal",
"CONTAE": "Baile Átha Cliath",
"POPULATION": 296020,
"PREVPOPULATION": 273991,
"MALES": "145,240",
"FEMALES": "150,780",
"HOUSESTOCK": "104,851",
"VACANT": "4,944",
"AREA": "448.1 km²",
"AGE": "34.3",
"GAEILGE": " ",
"PROVINCE": "Leinster",
"ID": "265002",
"CENTROID_X": "715859",
"CENTROID_Y": "750573",
"GlobalID": "da8a143e-499d-4407-ae87-36e6c9f68ef9",
"GUID": "DA8A143E-499D-4407-AE87-36E6C9F68EF9",
"Shape__Area": 0.0620038215995737,
"Shape__Length": 2.86766794208574,
"ABOUT": "Fingal County Council (FCC) is the authority responsible for local government in the county of Fingal and has 5 local electoral areas. "},
{
"OBJECTID": 3,
"COUNTY": "DUBLIN",
"ENGLISH": "Dun Laoghaire-Rathdown",
"CONTAE": "Baile Átha Cliath",
"POPULATION": 218018,
"PREVPOPULATION": 206261,
"MALES": "104,584",
"FEMALES": "113,434",
"HOUSESTOCK": "86,962",
"VACANT": "4,596",
"AREA": "127.3 km²",
"AGE": "39.0",
"ABOUT": "Dun Laoghaire-Rathdown County Council (DLRCC) is the authority responsible for local government in the county of Dun Laoghaire-Rathdown and has 6 local electoral areas. ",
"GAEILGE": " ",
"PROVINCE": "Leinster",
"ID": "265001",
"CENTROID_X": "719777",
"CENTROID_Y": "724822",
"GlobalID": "8cd118df-9362-4d15-8028-16cb016e942c",
"GUID": "8CD118DF-9362-4D15-8028-16CB016E942C",
"Shape__Area": 0.0170381226387334,
"Shape__Length": 0.808732445531413
}]
